[
    {
        "type": "tab",
        "id": "df2cd387.f2291",
        "label": "ECR"
    },
    {
        "id": "cb576020.9d1e4",
        "type": "ui_text",
        "z": "df2cd387.f2291",
        "tab": "692264eb.cffd6c",
        "name": "System Overloaded",
        "group": "",
        "order": 1,
        "format": "{{msg.payload.numToggled > msg.payload.numToggledMax}}",
        "x": 142,
        "y": 282,
        "wires": []
    },
    {
        "id": "9ca374ee.95dd58",
        "type": "inject",
        "z": "df2cd387.f2291",
        "name": "tick",
        "topic": "",
        "payload": "",
        "payloadType": "date",
        "repeat": "1",
        "crontab": "",
        "once": false,
        "x": 153,
        "y": 68,
        "wires": [
            []
        ]
    },
    {
        "id": "63d8d1be.a051e",
        "type": "http request",
        "z": "df2cd387.f2291",
        "name": "get data from integration",
        "method": "GET",
        "ret": "obj",
        "url": "$(ECR_get_url)",
        "x": 148,
        "y": 186,
        "wires": [
            [
                "cb576020.9d1e4"
            ]
        ]
    },
    {
        "id": "a290f55d.f853d8",
        "type": "subflow:9e21335d.82775",
        "z": "df2cd387.f2291",
        "name": "reactor",
        "x": 757.75,
        "y": 56,
        "wires": [
            []
        ]
    },
    {
        "id": "96e3cc5a.800af",
        "type": "inject",
        "z": "df2cd387.f2291",
        "name": "",
        "topic": "",
        "payload": "reactor",
        "payloadType": "str",
        "repeat": "",
        "crontab": "",
        "once": true,
        "x": 504.5,
        "y": 55,
        "wires": [
            [
                "a290f55d.f853d8"
            ]
        ]
    },
    {
        "id": "36c7746d.24027c",
        "type": "subflow:9e21335d.82775",
        "z": "df2cd387.f2291",
        "name": "beam_weapon",
        "x": 776,
        "y": 118,
        "wires": [
            []
        ]
    },
    {
        "id": "dd55b465.e57638",
        "type": "inject",
        "z": "df2cd387.f2291",
        "name": "",
        "topic": "",
        "payload": "beam_weapon",
        "payloadType": "str",
        "repeat": "",
        "crontab": "",
        "once": true,
        "x": 532.75,
        "y": 117,
        "wires": [
            [
                "36c7746d.24027c"
            ]
        ]
    },
    {
        "id": "f61a20ff.e827d",
        "type": "subflow:9e21335d.82775",
        "z": "df2cd387.f2291",
        "name": "missiles",
        "x": 754,
        "y": 180,
        "wires": [
            []
        ]
    },
    {
        "id": "44ed62a5.b7619c",
        "type": "inject",
        "z": "df2cd387.f2291",
        "name": "",
        "topic": "",
        "payload": "missiles",
        "payloadType": "str",
        "repeat": "",
        "crontab": "",
        "once": true,
        "x": 500.75,
        "y": 179,
        "wires": [
            [
                "f61a20ff.e827d"
            ]
        ]
    },
    {
        "id": "cfdfbb63.0ef3e8",
        "type": "subflow:9e21335d.82775",
        "z": "df2cd387.f2291",
        "name": "maneuvering",
        "x": 764,
        "y": 253,
        "wires": [
            []
        ]
    },
    {
        "id": "5867b9c7.f87b18",
        "type": "inject",
        "z": "df2cd387.f2291",
        "name": "",
        "topic": "",
        "payload": "maneuvering",
        "payloadType": "str",
        "repeat": "",
        "crontab": "",
        "once": true,
        "x": 520.75,
        "y": 252,
        "wires": [
            [
                "cfdfbb63.0ef3e8"
            ]
        ]
    },
    {
        "id": "976c4257.12505",
        "type": "subflow:9e21335d.82775",
        "z": "df2cd387.f2291",
        "name": "impulse_engine",
        "x": 772,
        "y": 324,
        "wires": [
            []
        ]
    },
    {
        "id": "9cdb869.a69e078",
        "type": "inject",
        "z": "df2cd387.f2291",
        "name": "",
        "topic": "",
        "payload": "impulse_engine",
        "payloadType": "str",
        "repeat": "",
        "crontab": "",
        "once": true,
        "x": 528.75,
        "y": 323,
        "wires": [
            [
                "976c4257.12505"
            ]
        ]
    },
    {
        "id": "9ece9648.8fbfa8",
        "type": "subflow:9e21335d.82775",
        "z": "df2cd387.f2291",
        "name": "warp_drive",
        "x": 762,
        "y": 399,
        "wires": [
            []
        ]
    },
    {
        "id": "9f5c0525.47d408",
        "type": "inject",
        "z": "df2cd387.f2291",
        "name": "",
        "topic": "",
        "payload": "warp_drive",
        "payloadType": "str",
        "repeat": "",
        "crontab": "",
        "once": true,
        "x": 508.75,
        "y": 398,
        "wires": [
            [
                "9ece9648.8fbfa8"
            ]
        ]
    },
    {
        "id": "1a518078.1e67a",
        "type": "subflow:9e21335d.82775",
        "z": "df2cd387.f2291",
        "name": "jump_drive",
        "x": 755,
        "y": 481,
        "wires": [
            []
        ]
    },
    {
        "id": "26adf0f1.cd61e",
        "type": "inject",
        "z": "df2cd387.f2291",
        "name": "",
        "topic": "",
        "payload": "jump_drive",
        "payloadType": "str",
        "repeat": "",
        "crontab": "",
        "once": true,
        "x": 501.75,
        "y": 480,
        "wires": [
            [
                "1a518078.1e67a"
            ]
        ]
    },
    {
        "id": "473f2fae.359aa",
        "type": "subflow:9e21335d.82775",
        "z": "df2cd387.f2291",
        "name": "front_shield",
        "x": 755,
        "y": 560,
        "wires": [
            []
        ]
    },
    {
        "id": "9e840b18.dd0e08",
        "type": "inject",
        "z": "df2cd387.f2291",
        "name": "",
        "topic": "",
        "payload": "front_shield",
        "payloadType": "str",
        "repeat": "",
        "crontab": "",
        "once": true,
        "x": 511.75,
        "y": 559,
        "wires": [
            [
                "473f2fae.359aa"
            ]
        ]
    },
    {
        "id": "2c5f8e69.a2bbd2",
        "type": "subflow:9e21335d.82775",
        "z": "df2cd387.f2291",
        "name": "rear_shield",
        "x": 755,
        "y": 634,
        "wires": [
            []
        ]
    },
    {
        "id": "214f8179.5c109e",
        "type": "inject",
        "z": "df2cd387.f2291",
        "name": "",
        "topic": "",
        "payload": "rear_shield",
        "payloadType": "str",
        "repeat": "",
        "crontab": "",
        "once": true,
        "x": 501.75,
        "y": 633,
        "wires": [
            [
                "2c5f8e69.a2bbd2"
            ]
        ]
    },
    {
        "id": "177372e.62ddf8d",
        "type": "ui_template",
        "z": "df2cd387.f2291",
        "tab": "692264eb.cffd6c",
        "name": "style override",
        "group": "",
        "order": 1,
        "format": "<style>\n.md-title {\n  display: none;\n}   \n</style>",
        "storeOutMessages": true,
        "fwdInMessages": true,
        "x": 142,
        "y": 380,
        "wires": [
            []
        ]
    }
]